apixwaves/__init__.py
apixwaves/conf.py
apixwaves/get_file_l2cwwic_from_date.py
apixwaves/get_full_path_from_measurement.py
apixwaves/list_files_l2_cwwic_between_dates.py
apixwaves/timeSpaceFileListQuery.py
apixwaves-0.2.dist-info/METADATA
apixwaves-0.2.dist-info/WHEEL
apixwaves-0.2.dist-info/top_level.txt
apixwaves-0.2.dist-info/RECORD
