Metadata-Version: 2.1
Name: apixwaves
Version: 0.2
Summary: Python library to compute cross spectra from SAR image
Author: Antoine Grouazel
License: GPL-3.0
Keywords: SAR,wave,reseach,cross-spectra
Classifier: Programming Language :: Python :: 3
Requires-Python: >=3.9
Requires-Dist: xarray
Requires-Dist: numpy
Requires-Dist: netCDF4
Requires-Dist: importlib-resources
Requires-Dist: tqdm
Requires-Dist: pillow
